[
	{
        "id": "Respuesta01",
    	"question": "¿Calidad del producto o servicio?",
        "anwers": [
            {
				"name": "Excelente",
				"value": "5"
            },
            {
				"name": "Bueno(a)",
				"value": "4"
            },
            {
				"name": "Normal",
				"value": "4"
            },
            {
				"name": "Regular",
				"value": "2"
            },
            {
				"name": "Malo",
				"value": "1"
            }
        ]
    },
    {
        "id": "Respuesta02",
    	"question": "¿Tiempo de espera en la atención?",
        "anwers": [
            {
            	"name": "Excelente",
            	"value": "5"
            },
            {
            	"name": "Bueno(a)",
            	"value": "4"
            },
            {
            	"name": "Normal",
            	"value": "4"
            },
            {
            	"name": "Regular",
            	"value": "2"
            },
            {
            	"name": "Malo",
            	"value": "1"
            }
        ]
    },
    {
        "id": "Respuesta03",
    	"question": "¿Imagen de las instalaciones?",
        "anwers": [
            {
            	"name": "Excelente",
            	"value": "5"
            },
            {
            	"name": "Bueno(a)",
            	"value": "4"
            },
            {
            	"name": "Normal",
            	"value": "4"
            },
            {
            	"name": "Regular",
            	"value": "2"
            },
            {
            	"name": "Malo",
            	"value": "1"
            }
        ]
    },
    {
        "id": "Respuesta04",
    	"question": "¿Disponibilidad de producto o servicio solicitado?",
        "anwers": [
            {
            	"name": "Excelente",
            	"value": "5"
            },
            {
            	"name": "Bueno(a)",
            	"value": "4"
            },
            {
            	"name": "Normal",
            	"value": "4"
            },
            {
            	"name": "Regular",
            	"value": "2"
            },
            {
            	"name": "Malo",
            	"value": "1"
            }
        ]
    },
    {
        "id": "Respuesta05",
    	"question": "¿Atención del personal?",
        "anwers": [
            {
                "name": "Malo",
                "value": "1"
            },
            {
                "name": "Regular",
                "value": "2"
            },
            {
                "name": "Normal",
                "value": "3"
            },
            {
                "name": "Bueno(a)",
                "value": "4"
            },
            {
            	"name": "Excelente",
            	"value": "5"
            }
        ]
    },
    {
        "id": "RangoEdad",
    	"question": "¿A qué grupo de edad pertenece?",
        "anwers": [
            {
            	"name": "12-17",
            	"value": "1"
            },
            {
            	"name": "18-33",
            	"value": "2"
            },
            {
            	"name": "34-45",
            	"value": "3"
            },
            {
            	"name": "46-55",
            	"value": "4"
            },	            
            {
            	"name": "56-64",
            	"value": "5"
            },
            {
            	"name": "65-73",
            	"value": "6"
            },
            {
            	"name": "74+",
            	"value": "7"
            }
        ]
    }
]